bxml/__init__.py
bxml/bxml.py
bxml/xmlmodule.cp312-win_amd64.pyd
bigger_xml-0.0.2.dist-info/LICENSE
bigger_xml-0.0.2.dist-info/METADATA
bigger_xml-0.0.2.dist-info/WHEEL
bigger_xml-0.0.2.dist-info/top_level.txt
bigger_xml-0.0.2.dist-info/RECORD
