Metadata-Version: 2.1
Name: bigger-xml
Version: 0.0.2
Summary: XML Generation Package to Generating Big xmls faster without any memory leakage issue
Home-page: https://github.com/bitu2765/bxml
Author: Bhautik Sudani
Author-email: bhautiksudani2765@gmail.com
Classifier: Programming Language :: Python :: 3
Classifier: Programming Language :: C
Classifier: License :: OSI Approved :: MIT License
Classifier: Operating System :: OS Independent
Classifier: Intended Audience :: Developers
Classifier: Intended Audience :: Information Technology
Classifier: Development Status :: 2 - Pre-Alpha
Classifier: Natural Language :: English
Classifier: Topic :: Software Development :: Libraries
Classifier: Topic :: Text Processing :: Markup
Classifier: Topic :: Utilities
Requires-Python: >=3.6
License-File: LICENSE
